[{"domain":"agronews.com.pl","links":1},{"domain":"agropolska.pl","links":1},{"domain":"amnesty.org.pl","links":1},{"domain":"android.com.pl","links":19},{"domain":"bit.ly","links":4},{"domain":"bitcoin.pl","links":1},{"domain":"bitcoinsv.pl","links":2},{"domain":"biznesalert.pl","links":6},{"domain":"bonilibri.pl","links":1},{"domain":"brandsit.pl","links":1},{"domain":"bruk-bet.pl","links":1},{"domain":"btcpolska.com","links":1},{"domain":"buff.ly","links":1},{"domain":"businessinsider.com.pl","links":2},{"domain":"cai24.pl","links":1},{"domain":"cenyrolnicze.pl","links":1},{"domain":"ceo.com.pl","links":1},{"domain":"chip.pl","links":1},{"domain":"citizengo.org","links":1},{"domain":"clinicaltrials.gov","links":1},{"domain":"comparic.pl","links":1},{"domain":"crobbe.com","links":1},{"domain":"curiouscat.qa","links":1},{"domain":"cyberdefence24.pl","links":1},{"domain":"cz24.news","links":1},{"domain":"dabrowa.pl","links":1},{"domain":"dlawas.info","links":1},{"domain":"dlvr.it","links":9},{"domain":"dorzeczy.pl","links":13},{"domain":"dw.com","links":2},{"domain":"dziennik.pl","links":13},{"domain":"dziennikbaltycki.pl","links":1},{"domain":"dziennikzarazy.pl","links":1},{"domain":"ecsc.eu","links":1},{"domain":"euractiv.pl","links":1},{"domain":"europa.eu","links":1},{"domain":"extremalny.pl","links":1},{"domain":"facebook.com","links":2},{"domain":"fakt.pl","links":8},{"domain":"farmer.pl","links":1},{"domain":"forsal.pl","links":4},{"domain":"ft.com","links":1},{"domain":"gazeta.lublin.pl","links":1},{"domain":"gazeta.pl","links":3},{"domain":"gazetaprawna.pl","links":5},{"domain":"godzinnik.pl","links":7},{"domain":"goo.gl","links":1},{"domain":"google.com","links":2},{"domain":"gosc.pl","links":1},{"domain":"gramofonia.com","links":1},{"domain":"ift.tt","links":3},{"domain":"infowire.pl","links":4},{"domain":"interfax.com.ua","links":1},{"domain":"interia.pl","links":25},{"domain":"investing.com","links":1},{"domain":"invst.ly","links":2},{"domain":"inwestycje.pl","links":2},{"domain":"is.gd","links":1},{"domain":"jauns.lv","links":1},{"domain":"klubygp.pl","links":1},{"domain":"kopalniawiedzy.pl","links":1},{"domain":"kresy24.pl","links":2},{"domain":"kronika24.pl","links":1},{"domain":"krytykapolityczna.pl","links":1},{"domain":"label-magazine.com","links":1},{"domain":"livesmarter.pl","links":1},{"domain":"livesport.com","links":1},{"domain":"lowcygier.pl","links":1},{"domain":"magnapolonia.org","links":2},{"domain":"mailchi.mp","links":1},{"domain":"mambiznes.pl","links":1},{"domain":"mandaryn1962.blogspot.com","links":1},{"domain":"meczyki.pl","links":1},{"domain":"medianarodowe.com","links":2},{"domain":"medonet.pl","links":1},{"domain":"moimokiem-bezfikcji.blogspot.com","links":6},{"domain":"motofaktor.pl","links":1},{"domain":"msn.com","links":85},{"domain":"mycompanypolska.pl","links":1},{"domain":"najpierwpolska.org","links":1},{"domain":"naszdziennik.pl","links":5},{"domain":"natemat.pl","links":1},{"domain":"naukadlaprzyrody.pl","links":1},{"domain":"newsweek.pl","links":10},{"domain":"niepoprawni.pl","links":3},{"domain":"niezalezna.pl","links":6},{"domain":"nop.org.pl","links":2},{"domain":"nowiny24.pl","links":1},{"domain":"nptv.pl","links":1},{"domain":"obserwatorgospodarczy.pl","links":1},{"domain":"oknonet.pl","links":2},{"domain":"oko.press","links":2},{"domain":"onet.pl","links":8},{"domain":"opoka.news","links":1},{"domain":"orange.pl","links":2},{"domain":"pap.pl","links":2},{"domain":"pb.pl","links":1},{"domain":"pch24.pl","links":3},{"domain":"ph-progress.pl","links":1},{"domain":"polsatnews.pl","links":5},{"domain":"polska-ie.com","links":19},{"domain":"polskanamorzu.pl","links":1},{"domain":"polskatimes.pl","links":4},{"domain":"polskawies24.pl","links":1},{"domain":"polskieradio.pl","links":1},{"domain":"polskieradio24.pl","links":3},{"domain":"portalmorski.pl","links":1},{"domain":"portalspozywczy.pl","links":1},{"domain":"pracowniakreska.eu","links":1},{"domain":"prawy.pl","links":1},{"domain":"press.pl","links":1},{"domain":"promocjeksiazkowe.pl","links":1},{"domain":"przegladbaltycki.pl","links":1},{"domain":"radio-polska.pl","links":1},{"domain":"radiomaryja.pl","links":3},{"domain":"radiozet.pl","links":18},{"domain":"rmf24.pl","links":29},{"domain":"rp.pl","links":4},{"domain":"salon24.pl","links":4},{"domain":"se.pl","links":2},{"domain":"sejm.gov.pl","links":1},{"domain":"space24.pl","links":1},{"domain":"spidersweb.pl","links":10},{"domain":"spotify.com","links":1},{"domain":"squidapp.co","links":1},{"domain":"swiatrolnika.info","links":1},{"domain":"t.co","links":1},{"domain":"telko.in","links":1},{"domain":"tiny.pl","links":1},{"domain":"tinyurl.com","links":4},{"domain":"transfery.info","links":2},{"domain":"transinfo.pl","links":1},{"domain":"tvn24.pl","links":50},{"domain":"tvp.info","links":9},{"domain":"tvp.pl","links":1},{"domain":"tvrepublika.pl","links":6},{"domain":"twitch.tv","links":4},{"domain":"tysol.pl","links":6},{"domain":"upflix.pl","links":7},{"domain":"volley.ru","links":1},{"domain":"wdolnymslasku.com","links":1},{"domain":"wgospodarce.pl","links":2},{"domain":"wiadomosci.com","links":1},{"domain":"wiadomoscihandlowe.pl","links":1},{"domain":"wiesci24.pl","links":3},{"domain":"wikipedia.org","links":2},{"domain":"wirtualnemedia.pl","links":2},{"domain":"wkurzeninakosciol.pl","links":1},{"domain":"wnp.pl","links":2},{"domain":"wolna-polska.pl","links":3},{"domain":"wolnemedia.net","links":1},{"domain":"wordpress.com","links":1},{"domain":"wp.pl","links":5},{"domain":"wpolityce.pl","links":1},{"domain":"wprost.pl","links":2},{"domain":"wpunkt.online","links":8},{"domain":"wwf.pl","links":1},{"domain":"www.gov.pl","links":1},{"domain":"wyborcza.biz","links":2},{"domain":"wyborcza.pl","links":11},{"domain":"youtu.be","links":19},{"domain":"youtube.com","links":4}]
