[{"domain":"acidigital.com","links":2},{"domain":"acistampa.com","links":2},{"domain":"aleteia.org","links":1},{"domain":"bit.ly","links":7},{"domain":"brandsit.pl","links":1},{"domain":"buff.ly","links":1},{"domain":"capitalbook.com.pl","links":1},{"domain":"catholicnewsagency.com","links":1},{"domain":"catholicregister.org","links":1},{"domain":"czytam.pl","links":1},{"domain":"dlvr.it","links":11},{"domain":"dorzeczy.pl","links":10},{"domain":"dzieje.pl","links":1},{"domain":"dziennik.pl","links":1},{"domain":"ekai.pl","links":6},{"domain":"exaudi.org","links":2},{"domain":"facebook.com","links":2},{"domain":"fakt.pl","links":1},{"domain":"fiat.fm","links":1},{"domain":"firstthings.com","links":1},{"domain":"flic.kr","links":1},{"domain":"forsal.pl","links":1},{"domain":"fronda.pl","links":3},{"domain":"ftmag.co","links":1},{"domain":"gazeta.pl","links":1},{"domain":"gloswielkopolski.pl","links":1},{"domain":"google.com","links":4},{"domain":"google.pl","links":1},{"domain":"gosc.pl","links":3},{"domain":"heraldmalaysia.com","links":1},{"domain":"ift.tt","links":6},{"domain":"interia.pl","links":4},{"domain":"jp2doc.pl","links":3},{"domain":"kath.ch","links":1},{"domain":"kresy.pl","links":1},{"domain":"krytykapolityczna.pl","links":3},{"domain":"lancasterdiocese.org.uk","links":1},{"domain":"lavsdeo.eu","links":1},{"domain":"londynek.net","links":1},{"domain":"mariologiapopular.com","links":1},{"domain":"misyjne.pl","links":1},{"domain":"msn.com","links":2},{"domain":"muzhp.pl","links":1},{"domain":"naszdziennik.pl","links":3},{"domain":"natemat.pl","links":1},{"domain":"niedziela.pl","links":5},{"domain":"niezalezna.pl","links":5},{"domain":"oko.press","links":1},{"domain":"onet.pl","links":11},{"domain":"opoka.news","links":4},{"domain":"polacywewloszech.com","links":1},{"domain":"polandin.com","links":1},{"domain":"polishnews.co.uk","links":2},{"domain":"polsatnews.pl","links":2},{"domain":"polska-ie.com","links":1},{"domain":"polskieradio.pl","links":1},{"domain":"polskieradio24.pl","links":12},{"domain":"przystanekhistoria.pl","links":2},{"domain":"radiomaryja.pl","links":17},{"domain":"radioszczecin.pl","links":4},{"domain":"religionenlibertad.com","links":2},{"domain":"rmf24.pl","links":2},{"domain":"rp.pl","links":1},{"domain":"salon24.pl","links":4},{"domain":"sejm.gov.pl","links":1},{"domain":"soundcloud.com","links":1},{"domain":"stacja7.pl","links":3},{"domain":"stefczyk.info","links":1},{"domain":"strzelnomojemiasto.blogspot.com","links":1},{"domain":"studioopinii.pl","links":1},{"domain":"tdpelmedia.com","links":2},{"domain":"tenetetraditiones.blogspot.com","links":1},{"domain":"tinyurl.com","links":1},{"domain":"trimarium.pl","links":1},{"domain":"tv-trwam.pl","links":1},{"domain":"tvn24.pl","links":1},{"domain":"tvp.info","links":12},{"domain":"tvp.pl","links":2},{"domain":"tvrepublika.pl","links":1},{"domain":"tysol.pl","links":9},{"domain":"wgospodarce.pl","links":1},{"domain":"wiadomosci.com","links":1},{"domain":"wiara.pl","links":2},{"domain":"wiez.pl","links":2},{"domain":"wikipedia.org","links":1},{"domain":"wnet.fm","links":1},{"domain":"wordpress.com","links":1},{"domain":"wp.pl","links":1},{"domain":"wpolityce.pl","links":3},{"domain":"wyborcza.pl","links":5},{"domain":"wykop.pl","links":1},{"domain":"wyszynskiprymas.pl","links":1},{"domain":"youtu.be","links":33},{"domain":"youtube.com","links":3}]
