[{"domain":"amnesty.org.pl","links":1},{"domain":"dziennik.pl","links":4},{"domain":"forsal.pl","links":1},{"domain":"goo.gl","links":2},{"domain":"icelandnews.is","links":1},{"domain":"kp.ru","links":1},{"domain":"nytimes.com","links":1},{"domain":"onet.pl","links":1},{"domain":"polishnews.co.uk","links":4},{"domain":"polsatnews.pl","links":1},{"domain":"polskatimes.pl","links":3},{"domain":"reddit.com","links":1},{"domain":"rp.pl","links":9},{"domain":"salon24.pl","links":1},{"domain":"thefad.pl","links":1},{"domain":"tvn24.pl","links":5},{"domain":"tvp.info","links":1},{"domain":"tygodnikpowszechny.pl","links":1},{"domain":"wyborcza.pl","links":1},{"domain":"youtu.be","links":1}]
