[{"domain":"albicla.com","links":1},{"domain":"auto-swiat.pl","links":1},{"domain":"bibula.com","links":1},{"domain":"bit.ly","links":4},{"domain":"biznesalert.pl","links":1},{"domain":"businessinsider.com.pl","links":1},{"domain":"codziennypoznan.pl","links":2},{"domain":"defence24.pl","links":1},{"domain":"dlvr.it","links":12},{"domain":"dobryruch.co.uk","links":1},{"domain":"donald.pl","links":1},{"domain":"dorzeczy.pl","links":2},{"domain":"dziennik.pl","links":2},{"domain":"dziennikpolski24.pl","links":1},{"domain":"episkopat.pl","links":2},{"domain":"facebook.com","links":4},{"domain":"fakt.pl","links":2},{"domain":"gazetakrakowska.pl","links":1},{"domain":"gazetaprawna.pl","links":1},{"domain":"goo.gl","links":8},{"domain":"gosc.pl","links":1},{"domain":"ift.tt","links":2},{"domain":"interia.pl","links":1},{"domain":"katowice24.info","links":1},{"domain":"kresy.pl","links":2},{"domain":"krytykapolityczna.pl","links":2},{"domain":"legaartis.pl","links":2},{"domain":"lifeinkrakow.pl","links":1},{"domain":"medonet.pl","links":1},{"domain":"msn.com","links":5},{"domain":"mycompanypolska.pl","links":1},{"domain":"natemat.pl","links":1},{"domain":"niezalezna.pl","links":7},{"domain":"oko.press","links":1},{"domain":"onet.pl","links":14},{"domain":"pb.pl","links":1},{"domain":"polskatimes.pl","links":4},{"domain":"polskieradio24.pl","links":4},{"domain":"radio5.com.pl","links":1},{"domain":"radomszczanska.pl","links":2},{"domain":"reuters.com","links":2},{"domain":"rmf24.pl","links":2},{"domain":"rp.pl","links":4},{"domain":"rynekzdrowia.pl","links":1},{"domain":"salon24.pl","links":3},{"domain":"spidersweb.pl","links":3},{"domain":"tenpoznan.pl","links":1},{"domain":"time.com","links":1},{"domain":"tvn24.pl","links":4},{"domain":"tvp.info","links":5},{"domain":"tvp.pl","links":1},{"domain":"tvrepublika.pl","links":1},{"domain":"tvs.pl","links":1},{"domain":"twitter.com","links":1},{"domain":"twojahistoria.pl","links":1},{"domain":"tysol.pl","links":1},{"domain":"ukrinform.net","links":1},{"domain":"vaticannews.va","links":1},{"domain":"wiesci24.pl","links":1},{"domain":"wikipedia.org","links":1},{"domain":"wirtualnemedia.pl","links":1},{"domain":"wolnemedia.net","links":1},{"domain":"wp.pl","links":2},{"domain":"wpolityce.pl","links":4},{"domain":"wroclife.pl","links":1},{"domain":"wyborcza.biz","links":4},{"domain":"wyborcza.pl","links":10},{"domain":"youtu.be","links":26},{"domain":"youtube.com","links":4}]
