[{"url_archive_id":"b22d6c64b3cf2be268bfd7bf3525a58d","twitter_url":"https://t.co/pT2kf0RNgA","query":"#WOŚP","discover_date":"2021-01-31","original_url":"https://www.siepomaga.pl/babciakasia","original_domain":"siepomaga.pl","content_type":"text/html","title":"\n\nSkarbonka Pomagacza Wiktoria Opolska - Skarbonka Babci Kasi | Siepomaga.pl\n"},{"url_archive_id":"b56b1f8f98f6f5e7adf80e98630812ea","twitter_url":"https://t.co/PhIFfOTomY","query":"#WOŚP","discover_date":"2021-01-31","original_url":"https://rzeczyodserca.pl/qna63k","original_domain":"rzeczyodserca.pl","content_type":"text/html","title":"Rzeczy od serca - Wspólne popołudnie z rodziną od Borysa Budki"},{"url_archive_id":"9df940e8fad221977275a40bee0ac53f","twitter_url":"https://t.co/MTdd1iWTTG","query":"#WOŚP","discover_date":"2021-01-31","original_url":"https://rybnik.naszemiasto.pl/wiemy-ile-zebrala-wosp-w-rybniku-super-wynik-rybniczanie/ar/c13-8114757","original_domain":"naszemiasto.pl","content_type":"text/html","title":"Wiemy ile zebrała WOŚP w Rybniku! Super wynik! Rybniczanie jesteście wielcy! | Rybnik Nasze Miasto"},{"url_archive_id":"bb8159f8d8d1e5bb462ce153b064cf8e","twitter_url":"https://t.co/7ZPuaFLRrf","query":"#WOŚP","discover_date":"2021-01-31","original_url":"https://www.wosp.org.pl/fundacja/jak-wspierac-wosp/wesprzyj-online/success","original_domain":"wosp.org.pl","content_type":"text/html","title":"Wpłać online - Fundacja Wielka Orkiestra Świątecznej Pomocy"},{"url_archive_id":"709fe2f6f9378ccdc97ff9db917c72e0","twitter_url":"https://t.co/QpQh0ABU7K","query":"#WOŚP","discover_date":"2021-01-31","original_url":"https://eskarbonka.wosp.org.pl/5nl5pd","original_domain":"wosp.org.pl","content_type":"text/html","title":"eSkarbonka"},{"url_archive_id":"2cfd9211e9e10df646a334ed950d749c","twitter_url":"https://t.co/Jlaqxjxnh7","query":"#WOŚP","discover_date":"2021-01-31","original_url":"https://www.salon24.pl/newsroom/1109988,owsiak-gani-tvp-w-czasie-finalu-wosp-nie-jestescie-moja-telewizja","original_domain":"salon24.pl","content_type":"text/html","title":"Owsiak gani TVP w czasie finału WOŚP. \"Nie jesteście moją telewizją\" - blog Salon24 news"},{"url_archive_id":"3eae610043db1a0ed0e2a5b5942558e5","twitter_url":"https://t.co/MFbn7hDyrK","query":"#WOŚP","discover_date":"2021-01-31","original_url":"https://www.deutschlandfunk.de/spenden-fuer-polens-kliniken-das-rote-herz-steht-fuer.795.de.html?dram:article_id=451387","original_domain":"deutschlandfunk.de","content_type":"text/html","title":"Spenden für Polens Kliniken - Das rote Herz steht für Millionen Zloty (Archiv)"},{"url_archive_id":"0f751e79573af53dd7afc4d25a7fda9d","twitter_url":"https://t.co/EimdI2AlEj","query":"#WOŚP","discover_date":"2021-01-31","original_url":"https://www.radiorodzina.pl/2021/01/31/koleje-dolnoslaskie-wspieraja-wosp/","original_domain":"radiorodzina.pl","content_type":"text/html","title":"Koleje Dolnośląskie wspierają WOŚP - Radio Rodzina"},{"url_archive_id":"7c3b0d381e0e0f70a5de1e9603fd0c1b","twitter_url":"https://t.co/xKJPu3IIpo","query":"#WOŚP","discover_date":"2021-01-31","original_url":"https://youtu.be/sEj8lUx0gwY","original_domain":"youtu.be","content_type":"text/html","title":"The Rolling Stones - Time Is On My Side - YouTube"},{"url_archive_id":"0bb0dfc2c43e356411cd2116c96b4e91","twitter_url":"https://t.co/p0POvaBI3l","query":"#WOŚP","discover_date":"2021-01-31","original_url":"https://kultura.gazeta.pl/kultura/7,127222,26742519,teatr-telewizji-wsparl-wosp-na-instagramie-i-wbil-szpile-tvp.html#s=BoxMMt2","original_domain":"gazeta.pl","content_type":"text/html"},{"url_archive_id":"82a888f535bcfeadc62ab2d0a318530f","twitter_url":"https://t.co/x9rliPT2Z6","query":"#WOŚP","discover_date":"2021-01-31","original_url":"https://twojaslupca.pl/absolutny-rekord-znow-wylicytowali-zlote-serduszko/","original_domain":"twojaslupca.pl","content_type":"text/html","title":"Absolutny rekord. Znów wylicytowali Złote Serduszko! - TwojaSłupca.pl"},{"url_archive_id":"9a669b41f2dde436d4e8b3f3c4f1e320","twitter_url":"https://t.co/S1BytNBSoq","query":"#WOŚP","discover_date":"2021-01-31","original_url":"https://eskarbonka.wosp.org.pl/wtwtng","original_domain":"wosp.org.pl","content_type":"text/html","title":"eSkarbonka"},{"url_archive_id":"fb1cdac9735c47fab4ed2e47f6ceaf84","twitter_url":"https://t.co/apS0h3KW7t","query":"#WOŚP","discover_date":"2021-01-31","original_url":"https://zyciestolicy.com.pl/trzaskowski-bedzie-zbieral-na-wosp-sam-dal-staruszce-20-groszy/","original_domain":"zyciestolicy.com.pl","content_type":"text/html","title":"Trzaskowski będzie zbierał na WOŚP – sam dał staruszce 20 groszy! - ZycieStolicy.com.pl"},{"url_archive_id":"3f0733c91bfe7af165ee175ad515c26b","twitter_url":"https://t.co/N0SjxiP8U7","query":"#WOŚP","discover_date":"2021-01-31","original_url":"https://eskarbonka.wosp.org.pl/2l6wq2","original_domain":"wosp.org.pl","content_type":"text/html","title":"eSkarbonka"},{"url_archive_id":"5fc261fde8110f53c1d00424308ef2df","twitter_url":"https://t.co/pTWq5KmySY","query":"#WOŚP","discover_date":"2021-01-31","original_url":"https://onet.pl/informacje/onetwiadomosci/swiatelko-do-nieba-efektowny-final-akcji-wosp-galeria/2j7wxlr,79cfc278","original_domain":"onet.pl","content_type":"text/html","title":"Światełko do nieba. Efektowny finał akcji WOŚP [GALERIA] - Wiadomości"},{"url_archive_id":"13307497101ad4e72e9c1fcb8a64f2dd","twitter_url":"https://t.co/lRRwFEWM01","query":"#WOŚP","discover_date":"2021-01-31","original_url":"https://tenpoznan.pl/wosp-trwa-liczenie-pieniedzy/","original_domain":"tenpoznan.pl","content_type":"text/html","title":"WOŚP: Trwa liczenie pieniędzy"},{"url_archive_id":"c1e9338b4542143fd61f61e39deeb837","twitter_url":"https://t.co/OFNb9iVnt4","query":"#WOŚP","discover_date":"2021-01-31","original_url":"https://www.instagram.com/p/CKuRda8hexd/?igshid=1sdfdxrku3bpn","original_domain":"instagram.com","content_type":"text/html","title":"\n@iszczecinek.pl on Instagram: “#29finałwośp #wośp #szczecinek #owsiak #wielkaorkiestraświątecznejpomocy”\n"},{"url_archive_id":"272cd4df4f09e8718f529eab8436f766","twitter_url":"https://t.co/KSPrqE3le7","query":"#WOŚP","discover_date":"2021-01-31","original_url":"https://eskarbonka.wosp.org.pl/ecw2g6","original_domain":"wosp.org.pl","content_type":"text/html","title":"eSkarbonka"},{"url_archive_id":"4ccd35e771daec38aeebbcce88f53194","twitter_url":"https://t.co/DID2dMrRwq","query":"#WOŚP","discover_date":"2021-01-31","original_url":"https://eskarbonka.wosp.org.pl/tl97yr","original_domain":"wosp.org.pl","content_type":"text/html","title":"eSkarbonka"},{"url_archive_id":"773f4d9b1a0058f2ecc906da7b75f24b","twitter_url":"https://t.co/BdjZRLpxd0","query":"#WOŚP","discover_date":"2021-01-31","original_url":"https://allegro.pl/oferta/obraz-na-poczatku-byl-chaos-na-wosp-10178160100?utm_medium=app_share&utm_source=facebook","original_domain":"allegro.pl","content_type":"text/html","title":"Obraz \"Na początku był Chaos\" na WOŚP - Aukcje WOŚP - Allegro.pl"},{"url_archive_id":"0bc077e6a4cb1b442ca622f1b8593f5a","twitter_url":"https://t.co/ZAMfrqPmkE","query":"#WOŚP","discover_date":"2021-01-31","original_url":"https://wosp.onet.pl/","original_domain":"onet.pl","content_type":"text/html","title":"29 Finał Wielkiej Orkiestry Świątecznej Pomocy - Onet.pl"},{"url_archive_id":"cd06dbe33ffe3212c9db0011ffd3af15","twitter_url":"https://t.co/NGYUv8yr6f","query":"#WOŚP","discover_date":"2021-01-31","original_url":"https://www.o2.pl/informacje/telewizja-republika-przerobila-serduszko-wosp-oplacilo-sie-burza-w-komentarzach-6603202695346720a","original_domain":"o2.pl","content_type":"text/html","title":"Telewizja Republika przerobiła serduszko WOŚP. Opłaciło się, burza w komentarzach - o2 - Serce Internetu"},{"url_archive_id":"ec1d020aefc2b920132c639f87e8dee3","twitter_url":"https://t.co/SH5MtRLkxc","query":"#WOŚP","discover_date":"2021-01-31","original_url":"https://www.wykop.pl/link/5932541/mocny-skrot-propagandowych-wiadomosci-tvpis-31-stycznia-2021/","original_domain":"wykop.pl","content_type":"text/html","title":"MOCNY Skrót propagandowych wiadomości TVPiS: 31 stycznia 2021 - Wykop.pl"},{"url_archive_id":"362fa6ab8287e439e2ddf17ff66adef4","twitter_url":"https://t.co/xKmBZ7nbSj","query":"#WOŚP","discover_date":"2021-01-31","original_url":"https://allegro.pl/oferta/polowanie-na-zorze-polarna-z-zorzowo-pl-10182548681","original_domain":"allegro.pl","content_type":"text/html","title":"POLOWANIE NA ZORZĘ POLARNĄ z ZORZOWO.pl - Aukcje WOŚP - Allegro.pl"},{"url_archive_id":"01de860c606d941767b523699ea4a0f1","twitter_url":"https://t.co/sZJqyE7IcJ","query":"#WOŚP","discover_date":"2021-01-31","original_url":"https://allegro.pl/oferta/indecent-noise-everything-is-connected-na-vinylu-10181475772","original_domain":"allegro.pl","content_type":"text/html","title":"Indecent Noise - Everything Is Connected na vinylu - Aukcje WOŚP - Allegro.pl"},{"url_archive_id":"9172c172dab9eed098014a6e19f40d92","twitter_url":"https://t.co/2tqQ1DGJq3","query":"#WOŚP","discover_date":"2021-01-31","original_url":"https://mobile.twitter.com/CierpialJarek/status/1355932018417291264","original_domain":"twitter.com","content_type":"text/html"},{"url_archive_id":"5010b804fa0c740b5cc11543f7ea050c","twitter_url":"https://t.co/dHAr92J5oY","query":"#WOŚP","discover_date":"2021-01-31","original_url":"https://krakow.wyborcza.pl/krakow/7,44425,26742512,wosp-2021-hejnal-z-dachu-tauron-areny-konczy-29-final-wosp.html","original_domain":"wyborcza.pl","content_type":"text/html","title":"Wyborcza.pl"},{"url_archive_id":"fe680826bf8ad20f5baf4f342189fcfc","twitter_url":"https://t.co/H1tu5IeTCp","query":"#WOŚP","discover_date":"2021-01-31","original_url":"https://linkd.pl/pupck","original_domain":"linkd.pl","content_type":"text/html","title":"linkd - skracanie linków  - pupck"},{"url_archive_id":"175271accd4bbcbf7e30c1740a17a682","twitter_url":"https://t.co/XFK3i7IVEz","query":"#WOŚP","discover_date":"2021-01-31","original_url":"https://wosp.vintom.com/62fc9c2a1c4fbc4037a60a71f12050aa?fbclid=IwAR1NuYCk0su1qH1V_Wx3wvnO1AJqbuWP2thgxvxf9o1fu92rIRMc0GTam0Q","original_domain":"vintom.com","content_type":"text/html","title":"WOŚP"},{"url_archive_id":"3d76e782bef92c7982c819ee020041dc","twitter_url":"https://t.co/n0v3zfroep","query":"#WOŚP","discover_date":"2021-01-31","original_url":"https://linkd.pl/pupca","original_domain":"linkd.pl","content_type":"text/html","title":"linkd - skracanie linków  - pupca"},{"url_archive_id":"e7614c4e4be2adff91e8e8ebe6186a07","twitter_url":"https://t.co/GZ3lbk3NS0","query":"#WOŚP","discover_date":"2021-01-31","original_url":"https://www.instagram.com/p/CKuKkranjIR/?igshid=p4ej1xax2do","original_domain":"instagram.com","content_type":"text/html","title":"\nMarcin Trzaska on Instagram: “Prosto ze sztabu WOŚP w Kątach Wrocławskich #wośp #katywroclawskie”\n"},{"url_archive_id":"ddf0c1e316dccd0992a43e2e51ebec20","twitter_url":"https://t.co/IiuLCmdrnN","query":"#WOŚP","discover_date":"2021-01-31","original_url":"https://pbs.twimg.com/ext_tw_video_thumb/1355960868136214532/pu/img/NngE50vnO2z4Ll9L?format=jpg&name=small","original_domain":"twimg.com","content_type":"image/jpeg"},{"url_archive_id":"e14f62a53735c0587b0f87eb10bbdf90","twitter_url":"https://t.co/p37inrR8UA","query":"#WOŚP","discover_date":"2021-01-31","original_url":"https://allegro.pl/oferta/obraz-autorstwa-rafala-knapczyka-10178480760","original_domain":"allegro.pl","content_type":"text/html","title":"Obraz autorstwa Rafała Knapczyka - Aukcje WOŚP - Allegro.pl"},{"url_archive_id":"295d75d421250fe80d7612427b77de99","twitter_url":"https://t.co/Bp4aeWjZBv","query":"#WOŚP","discover_date":"2021-01-31","original_url":"https://allegro.pl/oferta/piora-wieczne-od-pary-prezydenckiej-10144456803?utm_medium=app_share&utm_source=facebook","original_domain":"allegro.pl","content_type":"text/html","title":"Pióra wieczne od Pary Prezydenckiej - Aukcje WOŚP - Allegro.pl"},{"url_archive_id":"91d5e09597d213010764f62a18d33650","twitter_url":"https://t.co/zpj1bnTCMu","query":"#WOŚP","discover_date":"2021-01-31","original_url":"https://eskarbonka.wosp.org.pl/1ep7w4","original_domain":"wosp.org.pl","content_type":"text/html","title":"eSkarbonka"},{"url_archive_id":"2da734420f0c1e8b51149aa529699805","twitter_url":"https://t.co/gPg3DcQeRg","query":"#WOŚP","discover_date":"2021-01-31","original_url":"https://youtu.be/Brku_0L8hEE","original_domain":"youtu.be","content_type":"text/html","title":"Jeszcze W Zielone Gramy - YouTube"},{"url_archive_id":"e62ec641c39233ddc61fc00163f943b7","twitter_url":"https://t.co/GwNYAHroXz","query":"#WOŚP","discover_date":"2021-01-31","original_url":"https://eskarbonka.wosp.org.pl/kq1ech","original_domain":"wosp.org.pl","content_type":"text/html","title":"eSkarbonka"},{"url_archive_id":"d719e32fb07808ccdabd3c2f42bc38ae","twitter_url":"https://t.co/zenXMEiAjE","query":"#WOŚP","discover_date":"2021-01-31","original_url":"https://www.onet.pl/informacje/onetkrakow/ksiadz-z-krakowskiego-kosciola-przegania-wolontariuszy-wosp-z-chodnika-diabelska/xfr0264,79cfc278","original_domain":"onet.pl","content_type":"text/html","title":"WOŚP: Ksiądz z krakowskiego kościoła przegonił wolontariuszkę  - Kraków"},{"url_archive_id":"a93591ab1c69f97fa8f1f9ab7325de86","twitter_url":"https://t.co/yvYRv0pqQp","query":"#WOŚP","discover_date":"2021-01-31","original_url":"https://rzeszow-news.pl/29-final-wosp-w-rzeszowie-do-godz-1800-zebrano-ponad-70-tys-zl-foto/","original_domain":"rzeszow-news.pl","content_type":"text/html","title":"29. Finał WOŚP. W Rzeszowie do godz. 18:00 zebrano ponad 70 tys. zł"},{"url_archive_id":"10ba41cbbbe82c13d0bee90961d0c14e","twitter_url":"https://t.co/2YyLnilQUW","query":"#WOŚP","discover_date":"2021-01-31","original_url":"https://en.wosp.org.pl/","original_domain":"wosp.org.pl","content_type":"text/html","title":"The Great Orchestra of Christmas Charity - Great Orchestra of Christmas Charity Foundation"},{"url_archive_id":"a20807f16112ed93aa2d96b4ce86e650","twitter_url":"https://t.co/JIoDG8cQ57","query":"#WOŚP","discover_date":"2021-01-31","original_url":"https://youtu.be/TDACzKQpxFE","original_domain":"youtu.be","content_type":"text/html","title":"WOŚP Najman Stanowski - YouTube"},{"url_archive_id":"31cf3201036b8e34fb045005ac01b061","twitter_url":"https://t.co/rx2UXfKWyo","query":"#WOŚP","discover_date":"2021-01-31","original_url":"https://twitch.tv/jarock","original_domain":"twitch.tv","content_type":"text/html","title":"Twitch"},{"url_archive_id":"21880c4cfa7b6a955807a7455ff73dc6","twitter_url":"https://t.co/7GzW46sLDG","query":"#WOŚP","discover_date":"2021-01-31","original_url":"https://www.motocaina.pl/artykul/wylicytuj-przejazdzke-kultowym-porsche-718-cayman-i-przy-okazji-zrob-cos-dobrego-64670.html","original_domain":"motocaina.pl","content_type":"text/html","title":"Wylicytuj przejażdżkę kultowym Porsche 718 Cayman i przy okazji zrób coś dobrego!"},{"url_archive_id":"3d0b6ae6ee3cd31781a749a976ba4e1a","twitter_url":"https://t.co/Q8dlbdquQK","query":"#WOŚP","discover_date":"2021-01-31","original_url":"https://www.wosp.org.pl/fundacja/jak-wspierac-wosp/wesprzyj-online","original_domain":"wosp.org.pl","content_type":"text/html","title":"Wpłać online - Fundacja Wielka Orkiestra Świątecznej Pomocy"},{"url_archive_id":"446eb2d3de4fbe03e1ac4f15ec5b0ae5","twitter_url":"https://t.co/NMy6rqRiLe","query":"#WOŚP","discover_date":"2021-01-31","original_url":"https://tenpoznan.pl/poznan-morsowanie-dla-wosp/","original_domain":"tenpoznan.pl","content_type":"text/html","title":"Poznań: Morsowanie dla WOŚP"},{"url_archive_id":"44f3b8af8b72c152e06eb63359cb2d99","twitter_url":"https://t.co/EvTGCz4J8t","query":"#WOŚP","discover_date":"2021-01-31","original_url":"https://youtu.be/Cc0vOBSukvc","original_domain":"youtu.be","content_type":"text/html","title":"Najman Przekazuje Stanowskiemu Niebieską Kurtkę #MacinNajman #KrzysztofStanowski #Wośp - YouTube"},{"url_archive_id":"216a482cbfb0f3e31761d77521e52953","twitter_url":"https://t.co/rceJZvTx58","query":"#WOŚP","discover_date":"2021-01-31","original_url":"https://fb.watch/3maN_WpK1T/","original_domain":"fb.watch","content_type":"text/html","title":"Witajcie na wrocławskim Rynku ❤️👏🏻 My... - Prezydent Wrocławia Jacek Sutryk"},{"url_archive_id":"4927036e25da305f5045b78f20c38a15","twitter_url":"https://t.co/R8Jaccj0H4","query":"#WOŚP","discover_date":"2021-01-31","original_url":"https://allegro.pl/oferta/wosp-diadem-ewy-bilan-stoch-10148376141","original_domain":"allegro.pl","content_type":"text/html","title":"WOŚP - Diadem Ewy Bilan - Stoch - Aukcje WOŚP - Allegro.pl"},{"url_archive_id":"a9d88a60a134823afb9b60f41c4305bf","twitter_url":"https://t.co/FLy9vjn4h9","query":"#WOŚP","discover_date":"2021-01-31","original_url":"https://www.facebook.com/watch/live/?v=744748673140006&ref=watch_permalink","original_domain":"facebook.com","content_type":"text/html","title":"WOŚP Częstochowa - WOŚP Częstochowa | Facebook"},{"url_archive_id":"2c9db5db7ac0ef0e76234bdc87e2106e","twitter_url":"https://t.co/WxyuNF4NUF","query":"#WOŚP","discover_date":"2021-01-31","original_url":"https://allegro.pl/uzytkownik/zeroszesc","original_domain":"allegro.pl","content_type":"text/html","title":"Przedmioty użytkownika zeroszesc - Allegro.pl"},{"url_archive_id":"9c02c9b78e71a04efb08afda788c70bf","twitter_url":"https://t.co/WpseK9k447","query":"#WOŚP","discover_date":"2021-01-31","original_url":"https://allegro.pl/oferta/dzien-w-radiu-357-10133004271","original_domain":"allegro.pl","content_type":"text/html","title":"Dzień w Radiu 357 - Aukcje WOŚP - Allegro.pl"},{"url_archive_id":"3314e4736dd6770159a052840eeed39c","twitter_url":"https://t.co/23IWu7Iyzc","query":"#WOŚP","discover_date":"2021-01-31","original_url":"https://allegro.pl/oferta/zwiedzanie-browaru-waszczukowe-10132969014","original_domain":"allegro.pl","content_type":"text/html","title":"Zwiedzanie browaru Waszczukowe - Aukcje WOŚP - Allegro.pl"},{"url_archive_id":"3d838618d249b5e73c5c3c3eaa137970","twitter_url":"https://t.co/a4rgW7C7X8","query":"#WOŚP","discover_date":"2021-01-31","original_url":"https://www.wosp.org.pl/aktualnosci/przelew-blik-na-29-final-wosp","original_domain":"wosp.org.pl","content_type":"text/html","title":"Aktualności - Fundacja Wielka Orkiestra Świątecznej Pomocy"},{"url_archive_id":"fc1b092fc59c6c8926ed3a9cc07fdeb9","twitter_url":"https://t.co/EJju4SrUqC","query":"#WOŚP","discover_date":"2021-01-31","original_url":"https://allegro.pl/oferta/pokarm-dla-ptakow-slonecznik-czarny-2-5-kg-10171474310","original_domain":"allegro.pl","content_type":"text/html","title":"POKARM DLA PTAKÓW SŁONECZNIK CZARNY 2,5 KG 10171474310 - Allegro.pl"},{"url_archive_id":"40093400d006acd80aed949926bb1cc9","twitter_url":"https://t.co/nY7FOGKu1o","query":"#WOŚP","discover_date":"2021-01-31","original_url":"https://allegro.pl/uzytkownik/lukifera","original_domain":"allegro.pl","content_type":"text/html","title":"Przedmioty użytkownika lukifera - Allegro.pl"},{"url_archive_id":"5dce4a9992eed2911ca532d32f2bee74","twitter_url":"https://t.co/KVUkg4udeG","query":"#WOŚP","discover_date":"2021-01-31","original_url":"https://allegro.pl/oferta/drewniany-karmnik-dla-ptakow-budka-domek-9683874647","original_domain":"allegro.pl","content_type":"text/html","title":"Drewniany Karmnik dla Ptaków Budka Domek 9683874647 - Allegro.pl"},{"url_archive_id":"a9c0fe73c3769793c4456203bb0ad5ef","twitter_url":"https://t.co/H7ymjYz42E","query":"#WOŚP","discover_date":"2021-01-31","original_url":"https://allegro.pl/oferta/dzwonek-slonecznik-pokarm-dla-ptakow-zimujacych-10001984748","original_domain":"allegro.pl","content_type":"text/html","title":"DZWONEK SŁONECZNIK POKARM DLA PTAKÓW ZIMUJĄCYCH 10001984748 - Allegro.pl"},{"url_archive_id":"7c906b563dc459edadd75ebc44adaeb1","twitter_url":"https://t.co/jcGq6HJozm","query":"#WOŚP","discover_date":"2021-01-31","original_url":"https://allegro.pl/oferta/latka-linoryt-gryfa-1-10181408566","original_domain":"allegro.pl","content_type":"text/html","title":"\"Łatka\", linoryt gryfa - 1 - Aukcje WOŚP - Allegro.pl"},{"url_archive_id":"2d9f8e11c2bc02496488d883bb49875f","twitter_url":"https://t.co/4rYlom9APk","query":"#WOŚP","discover_date":"2021-01-31","original_url":"https://eskarbonka.wosp.org.pl/2vp6ja44?lang=en","original_domain":"wosp.org.pl","content_type":"text/html","title":"eSkarbonka"},{"url_archive_id":"ce6b8e879254e38edca380dd7183db0f","twitter_url":"https://t.co/SoFTaT3KM0","query":"#WOŚP","discover_date":"2021-01-31","original_url":"https://gazetaplus.pl/ksiadz-kowalczyk-wykluczyl-sympatykow-wosp-z-kosciola/32805/","original_domain":"gazetaplus.pl","content_type":"text/html","title":"Ksiądz Kowalczyk wykluczył sympatyków WOŚP z Kościoła."},{"url_archive_id":"667ee0e3c6b7a70d596d9035aee6c724","twitter_url":"https://t.co/n2fBVIjgoT","query":"#WOŚP","discover_date":"2021-01-31","original_url":"https://krakow.wyborcza.pl/krakow/7,44425,26741688,wosp-2021-krakowianie-szczodrze-wspieraja-orkiestre.html","original_domain":"wyborcza.pl","content_type":"text/html","title":"Wyborcza.pl"},{"url_archive_id":"9e0f075e10c4d25ceaa579ffa5b8ee88","twitter_url":"https://t.co/c3819niVYF","query":"#WOŚP","discover_date":"2021-01-31","original_url":"https://eskarbonka.wosp.org.pl/gywg7y","original_domain":"wosp.org.pl","content_type":"text/html","title":"eSkarbonka"},{"url_archive_id":"67c6a8c4751c8a4e664060f61557ea5a","twitter_url":"https://t.co/VbVZUmfrv5","query":"#WOŚP","discover_date":"2021-01-31","original_url":"https://youtu.be/fSBXp0zRZwE","original_domain":"youtu.be","content_type":"text/html","title":"Danuta Holecka chwali Jurka Owsiaka za WOŚP. - YouTube"},{"url_archive_id":"c82161a0e90f90858cb19a34571a945b","twitter_url":"https://t.co/cbLOqZKfNR","query":"#WOŚP","discover_date":"2021-01-31","original_url":"https://skoq.pl/","original_domain":"skoq.pl","content_type":"text/html","title":"Grafika Reklamowa | Marcin Skoczek skoQ.pl"},{"url_archive_id":"5c364ed09a2117a4968cf52ccd17c96f","twitter_url":"https://t.co/clw98ApHMv","query":"#WOŚP","discover_date":"2021-01-31","original_url":"https://youtu.be/iOAC1NLxFgM","original_domain":"youtu.be","content_type":"text/html","title":"Mini Festiwal Morsowania WOŚP 2021 Kołobrzeg - YouTube"},{"url_archive_id":"262a834962b4761b9a09f56772e857c5","twitter_url":"https://t.co/bxGlwfkzfn","query":"#WOŚP","discover_date":"2021-01-31","original_url":"https://allegro.pl/oferta/ksiazka-z-podpisami-prezydentow-miast-ump-10171794069","original_domain":"allegro.pl","content_type":"text/html","title":"Książka z podpisami Prezydentów miast UMP - Aukcje WOŚP - Allegro.pl"},{"url_archive_id":"3ae45bb323560c3cc4ebe9135df3e38f","twitter_url":"https://t.co/Lx2E5k70z0","query":"#WOŚP","discover_date":"2021-01-31","original_url":"https://www.instagram.com/p/CKtuhhnJe1j/?igshid=hg2sx2in7mco","original_domain":"instagram.com","content_type":"text/html","title":"\nMarek Długi on Instagram: “❤️❤️❤️ WOŚP 2021 ❤️❤️❤️\nZostaw w kom ❤️\n#wośp #wośp2021 #mama #córka #mamaicórka #misiaija”\n"},{"url_archive_id":"4916d552a5722deee1f6c16a578e96f5","twitter_url":"https://t.co/Er6KPKsTgQ","query":"#WOŚP","discover_date":"2021-01-31","original_url":"https://solarpoweredblonde.com/ultimate-two-week-sri-lanka-itinerary/?unapproved=1383&moderation-hash=f4a1a45c94aee83c31a6d1ffc8bdf3fe#comment-1383","original_domain":"solarpoweredblonde.com","content_type":"text/html","title":"Ultimate Two Week Sri Lanka Itinerary - Solarpoweredblonde"},{"url_archive_id":"11e0623354e9c8d2d7aaf7fcb0b92c64","twitter_url":"https://t.co/65cu7lnAQZ","query":"#WOŚP","discover_date":"2021-01-31","original_url":"https://fb.watch/3mv-Xa0VIF/","original_domain":"fb.watch","content_type":"text/html","title":"Sosnowiec łączy - WOSP 2021 - SOSNOWIEC | Facebook"}]
