[{"domain":"101010.pl","links":1},{"domain":"300gospodarka.pl","links":4},{"domain":"35mm.online","links":1},{"domain":"abilet.pl","links":1},{"domain":"adamaswtrasie.blogspot.com","links":2},{"domain":"agropolska.pl","links":1},{"domain":"alebank.pl","links":1},{"domain":"alleysport.com","links":1},{"domain":"amazon.pl","links":2},{"domain":"ampproject.org","links":1},{"domain":"apple.com","links":1},{"domain":"aszdziennik.pl","links":1},{"domain":"auto-swiat.pl","links":1},{"domain":"banbye.com","links":1},{"domain":"bankier.pl","links":2},{"domain":"batory.org.pl","links":1},{"domain":"beatit.tv","links":1},{"domain":"beincrypto.com","links":1},{"domain":"belsat.eu","links":1},{"domain":"benchmark.pl","links":1},{"domain":"bezprawnik.pl","links":1},{"domain":"bibula.com","links":1},{"domain":"bit.ly","links":16},{"domain":"bitcoin.pl","links":5},{"domain":"bitcoinmagazine.com","links":11},{"domain":"biznesalert.pl","links":7},{"domain":"biznesinfo.pl","links":2},{"domain":"bloglovin.com","links":1},{"domain":"bonito.pl","links":1},{"domain":"booklips.pl","links":1},{"domain":"breaking7.com","links":1},{"domain":"btcpolska.com","links":5},{"domain":"buff.ly","links":65},{"domain":"businessinsider.com.pl","links":15},{"domain":"calendar-yearly.com","links":1},{"domain":"cashless.pl","links":2},{"domain":"check-host.net","links":4},{"domain":"chnnews.pl","links":3},{"domain":"chrystusowcy.pl","links":2},{"domain":"chwalazapomniana.pl","links":1},{"domain":"ciekaweliczby.pl","links":1},{"domain":"ciekawostkihistoryczne.pl","links":1},{"domain":"cire.pl","links":1},{"domain":"cleanerenergy.pl","links":2},{"domain":"coindesk.com","links":17},{"domain":"cointelegraph.com","links":2},{"domain":"coinyuppie.com","links":3},{"domain":"crowdmedia.pl","links":1},{"domain":"crypto.com","links":1},{"domain":"cyberdefence24.pl","links":3},{"domain":"czestochowskie24.pl","links":2},{"domain":"dabrowa.pl","links":1},{"domain":"dailycoin.com","links":3},{"domain":"dailyhodl.com","links":6},{"domain":"dailyweb.pl","links":1},{"domain":"dakowski.pl","links":1},{"domain":"debata.olsztyn.pl","links":2},{"domain":"defence24.pl","links":3},{"domain":"discord.gg","links":1},{"domain":"disinformate.com","links":12},{"domain":"dlapolski.pl","links":1},{"domain":"dlvr.it","links":80},{"domain":"dorzeczy.pl","links":23},{"domain":"dw.com","links":5},{"domain":"dzieje.pl","links":1},{"domain":"dziennik.pl","links":33},{"domain":"dziennikzachodni.pl","links":1},{"domain":"dziennikzwiazkowy.com","links":1},{"domain":"e-chorzow.com","links":1},{"domain":"ea.com","links":1},{"domain":"ebetx.link","links":17},{"domain":"ekai.pl","links":2},{"domain":"energetyka24.com","links":3},{"domain":"episkopat.pl","links":1},{"domain":"eppgroup.eu","links":1},{"domain":"esanok.pl","links":1},{"domain":"eska.pl","links":1},{"domain":"euractiv.pl","links":3},{"domain":"europedirect-slaskie.pl","links":1},{"domain":"eventcards.pl","links":1},{"domain":"ewybory.eu","links":1},{"domain":"facebook.com","links":9},{"domain":"fakt.pl","links":14},{"domain":"fb.watch","links":6},{"domain":"felineus.org","links":3},{"domain":"flashscore.pl","links":1},{"domain":"flightradar24.com","links":1},{"domain":"focusonbusiness.eu","links":1},{"domain":"forbes.pl","links":2},{"domain":"forsal.pl","links":21},{"domain":"fronda.pl","links":4},{"domain":"g.co","links":1},{"domain":"g.page","links":1},{"domain":"gamingdeputy.com","links":1},{"domain":"gate.io","links":1},{"domain":"gazeta.pl","links":4},{"domain":"gazetalubuska.pl","links":1},{"domain":"gazetapolska.pl","links":1},{"domain":"gazetaprawna.pl","links":10},{"domain":"getrevue.co","links":1},{"domain":"gloria.tv","links":1},{"domain":"gloswielkopolski.pl","links":2},{"domain":"gloswolnosci.pl","links":1},{"domain":"goal.pl","links":1},{"domain":"gol24.pl","links":1},{"domain":"goo.gl","links":7},{"domain":"google.com","links":7},{"domain":"google.pl","links":1},{"domain":"gosc.pl","links":2},{"domain":"gpcodziennie.pl","links":1},{"domain":"gpsdlaaktywnych.pl","links":1},{"domain":"historykon.pl","links":2},{"domain":"home.blog","links":1},{"domain":"hotels-with-sauna.com","links":1},{"domain":"i.pl","links":20},{"domain":"ift.tt","links":9},{"domain":"infoans.org","links":2},{"domain":"infosport.pl","links":1},{"domain":"infowire.pl","links":6},{"domain":"innpoland.pl","links":1},{"domain":"inspiracjewmoimmieszkaniu.blogspot.com","links":1},{"domain":"instagram.com","links":2},{"domain":"interia.pl","links":17},{"domain":"inwestycje.pl","links":1},{"domain":"jagiellonia.org","links":1},{"domain":"jakon-hale.pl","links":1},{"domain":"jaro-aleks-cern.blogspot.com","links":1},{"domain":"kalendarzrolnikow.pl","links":1},{"domain":"klassikauto.pl","links":1},{"domain":"klubjagiellonski.pl","links":1},{"domain":"klubpodroznikow.com","links":2},{"domain":"komputerswiat.pl","links":1},{"domain":"korso24.pl","links":1},{"domain":"kronika24.pl","links":1},{"domain":"kurs-na-funta.pl","links":2},{"domain":"legaartis.pl","links":9},{"domain":"legnica24.eu","links":1},{"domain":"linuxiarze.pl","links":1},{"domain":"livemint.com","links":1},{"domain":"londynek.net","links":3},{"domain":"magnapolonia.org","links":2},{"domain":"mamstartup.pl","links":1},{"domain":"mandaryn1962.blogspot.com","links":1},{"domain":"mashable.com","links":1},{"domain":"mbda-systems.com","links":1},{"domain":"mcdonalds.pl","links":1},{"domain":"metanews.com","links":2},{"domain":"michalwyszynski.com","links":1},{"domain":"mkszaglebie.pl","links":2},{"domain":"moimokiem-bezfikcji.blogspot.com","links":6},{"domain":"money.pl","links":9},{"domain":"monitorwolynski.com","links":1},{"domain":"mpress.pl","links":1},{"domain":"msn.com","links":496},{"domain":"myslpolska.info","links":1},{"domain":"NA.NA","links":5},{"domain":"nac.gov.pl","links":1},{"domain":"naekranie.pl","links":1},{"domain":"napsitemat.pl","links":1},{"domain":"naszahistoria.pl","links":1},{"domain":"naszeblogi.pl","links":22},{"domain":"naszemiasto.pl","links":1},{"domain":"natemat.pl","links":5},{"domain":"natorze.pl","links":1},{"domain":"nauka-polska.pl","links":1},{"domain":"naukaoklimacie.pl","links":1},{"domain":"nczas.com","links":8},{"domain":"newsweek.pl","links":51},{"domain":"nflix.pl","links":3},{"domain":"nftgo.io","links":1},{"domain":"nftmagazine.com","links":1},{"domain":"niedziela.pl","links":1},{"domain":"niepoprawni.pl","links":2},{"domain":"niezalezna.pl","links":12},{"domain":"nowosci.com.pl","links":1},{"domain":"o2.pl","links":2},{"domain":"obserwatorgospodarczy.pl","links":1},{"domain":"odkrywamyzakryte.com","links":1},{"domain":"odstraszanie.pl","links":1},{"domain":"ofeminin.pl","links":1},{"domain":"oko.press","links":1},{"domain":"okrakow.pl","links":2},{"domain":"olejekcbdsklep.com.pl","links":1},{"domain":"onet.pl","links":16},{"domain":"opoka.org.pl","links":3},{"domain":"orange.pl","links":3},{"domain":"pap.pl","links":9},{"domain":"pb.pl","links":5},{"domain":"pch24.pl","links":1},{"domain":"peakd.com","links":1},{"domain":"picturesdown.com","links":1},{"domain":"pilkarski.biz","links":2},{"domain":"pk.gov.pl","links":1},{"domain":"player.pl","links":1},{"domain":"plse.org.pl","links":1},{"domain":"plus.pl","links":1},{"domain":"poczta-polska.pl","links":1},{"domain":"poinformowani.pl","links":3},{"domain":"polandasia.com","links":1},{"domain":"polishsnailholding.com","links":4},{"domain":"politico.eu","links":1},{"domain":"polityka.pl","links":1},{"domain":"politykazdrowotna.com","links":1},{"domain":"polka.az","links":1},{"domain":"polsatnews.pl","links":4},{"domain":"polsatsport.pl","links":6},{"domain":"polska-ie.com","links":76},{"domain":"polska-org.pl","links":1},{"domain":"polska-pilka.pl","links":1},{"domain":"polska2050.pl","links":1},{"domain":"polskieradio.com","links":1},{"domain":"polskihokej.tv","links":1},{"domain":"polskiobserwator.de","links":3},{"domain":"pomorska.pl","links":1},{"domain":"pomponik.pl","links":2},{"domain":"portalsamorzadowy.pl","links":2},{"domain":"portalspozywczy.pl","links":2},{"domain":"ppe.pl","links":5},{"domain":"pracownia.org.pl","links":1},{"domain":"prawicowyinternet.pl","links":1},{"domain":"prawy.pl","links":3},{"domain":"press.pl","links":5},{"domain":"pulshr.pl","links":3},{"domain":"pulspz.pl","links":1},{"domain":"radiomaryja.pl","links":9},{"domain":"radionadzieja.pl","links":1},{"domain":"radioszczecin.pl","links":2},{"domain":"radiowarszawa.com.pl","links":2},{"domain":"radiozet.pl","links":26},{"domain":"rdc.pl","links":1},{"domain":"regiowyniki.pl","links":5},{"domain":"resetobywatelski.pl","links":1},{"domain":"rmf24.pl","links":51},{"domain":"rp.pl","links":14},{"domain":"rugbyeurope.eu","links":1},{"domain":"rumble.com","links":1},{"domain":"sablane.pl","links":1},{"domain":"sadifanalytics.com","links":1},{"domain":"sadyogrody.pl","links":1},{"domain":"salon24.pl","links":6},{"domain":"schiffradio.com","links":1},{"domain":"se.pl","links":15},{"domain":"skijumping.pl","links":1},{"domain":"skokinarciarskie.pl","links":2},{"domain":"slaskaopinia.pl","links":1},{"domain":"spidersweb.pl","links":7},{"domain":"sportmarketing.pl","links":1},{"domain":"sportowaksiazkaroku.pl","links":1},{"domain":"sports.gg","links":1},{"domain":"spotify.com","links":3},{"domain":"squidapp.co","links":1},{"domain":"stanpolityki.pl","links":1},{"domain":"stooq.pl","links":1},{"domain":"strefainwestorow.pl","links":5},{"domain":"super-basket.pl","links":1},{"domain":"swiatzwierzat.pl","links":1},{"domain":"swidnica24.pl","links":1},{"domain":"szczecinek.com","links":2},{"domain":"t.me","links":7},{"domain":"tabletowo.pl","links":1},{"domain":"teatr2strefa.pl","links":1},{"domain":"teatrnn.pl","links":1},{"domain":"tedeum.pl","links":1},{"domain":"telepolis.pl","links":6},{"domain":"tenisbydawid.pl","links":1},{"domain":"theverge.com","links":1},{"domain":"tiktok.com","links":7},{"domain":"tm8185.net","links":1},{"domain":"tokfm.pl","links":1},{"domain":"tolkniety.blogspot.com","links":1},{"domain":"tomaszrogus.pl","links":1},{"domain":"transfery.info","links":1},{"domain":"transinfo.pl","links":1},{"domain":"triathlonlife.pl","links":1},{"domain":"tvn24.pl","links":119},{"domain":"tvp.info","links":19},{"domain":"tvp.pl","links":10},{"domain":"tvrepublika.pl","links":11},{"domain":"twitch.tv","links":10},{"domain":"twittertwins.pl","links":1},{"domain":"tylkoszachy.blogspot.com","links":1},{"domain":"tysol.pl","links":32},{"domain":"ukiel.info","links":1},{"domain":"upflix.pl","links":19},{"domain":"weatheronline.pl","links":1},{"domain":"weszlo.com","links":2},{"domain":"wgospodarce.pl","links":3},{"domain":"wiadomosci.com","links":4},{"domain":"wiadomoscihandlowe.pl","links":4},{"domain":"wiesci24.pl","links":5},{"domain":"wiez.pl","links":1},{"domain":"wikipedia.org","links":5},{"domain":"wirtualnemedia.pl","links":8},{"domain":"wnet.fm","links":1},{"domain":"wnp.pl","links":11},{"domain":"wolna-polska.com","links":1},{"domain":"wolnelektury.pl","links":1},{"domain":"wolnemedia.net","links":4},{"domain":"wordpress.com","links":3},{"domain":"wp.pl","links":11},{"domain":"wpolityce.pl","links":16},{"domain":"wprost.pl","links":7},{"domain":"wsieciprawdy.pl","links":1},{"domain":"wspolczesna.pl","links":1},{"domain":"wszystkiedowody.pl","links":1},{"domain":"wszystkoconajwazniejsze.pl","links":3},{"domain":"www.gdynia.pl","links":1},{"domain":"www.gov.pl","links":4},{"domain":"wyborcza.biz","links":2},{"domain":"wyborcza.pl","links":18},{"domain":"youtu.be","links":113},{"domain":"youtube.com","links":45},{"domain":"zarabiajnabankach.pl","links":1},{"domain":"zawszepomorze.pl","links":3},{"domain":"zerohedge.com","links":1},{"domain":"zlaambasada.pl","links":1},{"domain":"zpr.io","links":1},{"domain":"zyciestolicy.com.pl","links":1}]
